README.md
licence.txt
setup.py
pro_video_ferramentas/__init__.py
pro_video_ferramentas/camera.py
pro_video_ferramentas/video.py
pro_video_ferramentas_maciel_2024.egg-info/PKG-INFO
pro_video_ferramentas_maciel_2024.egg-info/SOURCES.txt
pro_video_ferramentas_maciel_2024.egg-info/dependency_links.txt
pro_video_ferramentas_maciel_2024.egg-info/top_level.txt