Metadata-Version: 2.1
Name: pro-video-ferramentas-maciel-2024
Version: 1.0
Summary: Este pacote irá fornecer ferramentas de processamento de vídeo
Author: maciel
Author-email: macielfb@gmail.com
Keywords: camera,video,processamento
License-File: licence.txt
